zope.app.renderer-5.0-py3.9-nspkg.pth
zope/app/renderer/__init__.py
zope/app/renderer/configure.zcml
zope/app/renderer/i18n.py
zope/app/renderer/interfaces.py
zope/app/renderer/plaintext.py
zope/app/renderer/rest.py
zope/app/renderer/stx.py
zope/app/renderer/vocabulary.py
zope/app/renderer/tests/__init__.py
zope/app/renderer/tests/test_renderers.py
zope/app/renderer/tests/test_vocabulary.py
zope.app.renderer-5.0.dist-info/LICENSE.txt
zope.app.renderer-5.0.dist-info/METADATA
zope.app.renderer-5.0.dist-info/WHEEL
zope.app.renderer-5.0.dist-info/namespace_packages.txt
zope.app.renderer-5.0.dist-info/top_level.txt
zope.app.renderer-5.0.dist-info/RECORD
