Metadata-Version: 2.1
Name: zope.app.renderer
Version: 5.0
Summary: Text Renderer Framework
Home-page: http://github.com/zopefoundation/zope.app.renderer
Author: Zope Corporation and Contributors
Author-email: zope-dev@zope.dev
License: ZPL 2.1
Keywords: zope3 renderer text rest rst stx
Classifier: Development Status :: 5 - Production/Stable
Classifier: Environment :: Web Environment
Classifier: Intended Audience :: Developers
Classifier: License :: OSI Approved :: Zope Public License
Classifier: Programming Language :: Python
Classifier: Programming Language :: Python :: 3
Classifier: Programming Language :: Python :: 3.7
Classifier: Programming Language :: Python :: 3.8
Classifier: Programming Language :: Python :: 3.9
Classifier: Programming Language :: Python :: 3.10
Classifier: Programming Language :: Python :: 3.11
Classifier: Programming Language :: Python :: Implementation :: CPython
Classifier: Programming Language :: Python :: Implementation :: PyPy
Classifier: Natural Language :: English
Classifier: Operating System :: OS Independent
Classifier: Topic :: Internet :: WWW/HTTP
Classifier: Framework :: Zope :: 3
Requires-Python: >=3.7
License-File: LICENSE.txt
Requires-Dist: setuptools
Requires-Dist: docutils (>=0.5)
Requires-Dist: roman
Requires-Dist: zope.component
Requires-Dist: zope.configuration
Requires-Dist: zope.i18nmessageid
Requires-Dist: zope.interface
Requires-Dist: zope.publisher
Requires-Dist: zope.schema
Requires-Dist: zope.structuredtext
Provides-Extra: test
Requires-Dist: zope.testing ; extra == 'test'
Requires-Dist: zope.testrunner ; extra == 'test'
